_coneref.cp38-win_amd64.pyd
coneref/__init__.py
coneref/cones_utils.py
coneref/cvxpy_interface.py
tests/__init__.py
tests/test_cones.py
tests/test_one.py
coneref-0.2.2.dist-info/LICENSE
coneref-0.2.2.dist-info/METADATA
coneref-0.2.2.dist-info/WHEEL
coneref-0.2.2.dist-info/top_level.txt
coneref-0.2.2.dist-info/RECORD
