Metadata-Version: 2.1
Name: coneref
Version: 0.2.2
Home-page: https://github.com/dance858/coneref
Author: Daniel Cederberg, Stephen Boyd
License: MIT License
Classifier: Programming Language :: Python :: 3
License-File: LICENSE
Requires-Dist: numpy (>=1.15)
Requires-Dist: scs (>=2.0.2)
Requires-Dist: scipy (>=1.1.0)
Requires-Dist: pybind11 (>=2.4)
Requires-Dist: cvxpy (>=1.1.0)
